hmxlabs/hplx/__init__.py
hmxlabs/hplx/__main__.py
hmxlabs/hplx/hpl_input.py
hmxlabs/hplx/hpl_results.py
hmxlabs/hplx/hplx.py
hmxlabs.hplx-0.4.3.dist-info/LICENSE
hmxlabs.hplx-0.4.3.dist-info/METADATA
hmxlabs.hplx-0.4.3.dist-info/WHEEL
hmxlabs.hplx-0.4.3.dist-info/entry_points.txt
hmxlabs.hplx-0.4.3.dist-info/top_level.txt
hmxlabs.hplx-0.4.3.dist-info/RECORD
