Metadata-Version: 2.1
Name: hmxlabs.hplx
Version: 0.4.3
Summary: This project is a collection of tools to help use the HPL benchmark. See https://github.com/hmxlabs/hplx/blob/main/README.md for more information.
Author-email: HMx Labs <comms@hmxlabs.uk>
Project-URL: Homepage, https://github.com/hmxlabs/hplx/
Project-URL: HMxLabs, http://hmxlabs.io
Classifier: Programming Language :: Python :: 3.10
Classifier: License :: OSI Approved :: MIT License
Classifier: Operating System :: OS Independent
Classifier: Environment :: Console
Classifier: Intended Audience :: Developers
Requires-Python: >=3.10
License-File: LICENSE
Requires-Dist: psutil~=5.9
Requires-Dist: py-cpuinfo==9.0.0
